LICENSE.txt
README.md
setup.cfg
setup.py
LRU_pytorch/LRU.py
LRU_pytorch/__init__.py
LRU_pytorch.egg-info/PKG-INFO
LRU_pytorch.egg-info/SOURCES.txt
LRU_pytorch.egg-info/dependency_links.txt
LRU_pytorch.egg-info/requires.txt
LRU_pytorch.egg-info/top_level.txt